src/bayesian_pack_dv_lp-dev/__init__.py
src/bayesian_pack_dv_lp-dev/network.py
src/bayesian_pack_dv_lp-dev/node.py
bayesian_pack_dv_lp_dev-0.3.dist-info/METADATA
bayesian_pack_dv_lp_dev-0.3.dist-info/WHEEL
bayesian_pack_dv_lp_dev-0.3.dist-info/licenses/LICENSE.txt
bayesian_pack_dv_lp_dev-0.3.dist-info/RECORD
