Metadata-Version: 2.1
Name: bayesian_pack_dv_lp-dev
Version: 0.3
Summary: An abstraction on bayesian network.
Project-URL: Homepage, https://github.com/LPELCRACK896/bayes-probabilistic-divinas.git
Author-email: DVN <lp-dev@gmail.com>
License-File: LICENSE.txt
Classifier: License :: OSI Approved :: MIT License
Classifier: Operating System :: OS Independent
Classifier: Programming Language :: Python :: 3
Requires-Python: >=3.9
